astro_gdt_ipn-1.0.0.dist-info/licenses/license.txt
gdt/ipn/__init__.py
gdt/ipn/grb.py
gdt/ipn/instrument.py
gdt/ipn/algorithms/__init__.py
gdt/ipn/algorithms/annulus.py
gdt/ipn/algorithms/ccf.py
astro_gdt_ipn-1.0.0.dist-info/METADATA
astro_gdt_ipn-1.0.0.dist-info/WHEEL
astro_gdt_ipn-1.0.0.dist-info/top_level.txt
astro_gdt_ipn-1.0.0.dist-info/RECORD
