Metadata-Version: 2.4
Name: astro-gdt-ipn
Version: 1.0.0
Summary: Gamma-ray Data Tools: IPN Gamma-ray Localization Toolkit
Author: Corinne Fletcher, Rachel Hamburg, Adam Goldstein, Peter Veres, Michelle Hui, Dmitry Svinkin
Author-email: STI-Software@usra.edu
License-Expression: Apache-2.0
Keywords: astronomy,gammaray,gamma-ray,usra
Classifier: Development Status :: 5 - Production/Stable
Classifier: Programming Language :: Python :: 3
Classifier: Programming Language :: Python :: 3.11
Classifier: Operating System :: MacOS
Classifier: Operating System :: POSIX :: Linux
Classifier: Topic :: Scientific/Engineering :: Astronomy
Classifier: Topic :: Software Development :: Libraries
Requires-Python: >=3.11
License-File: license.txt
Requires-Dist: astro-gdt>=2.2.0
Requires-Dist: astro-gdt-fermi>=2.2.0
Requires-Dist: notebook>=7.5.0
Dynamic: license-file
